{
    "sourceFile": "src/main/java/client/ui/GameOverPopup.java",
    "activeCommit": 0,
    "commits": [
        {
            "activePatchIndex": 0,
            "patches": [
                {
                    "date": 1764830378833,
                    "content": "Index: \n===================================================================\n--- \n+++ \n"
                }
            ],
            "date": 1764830378833,
            "name": "Commit-0",
            "content": "// src/main/java/com/client/ui/GameOverPopup.java\r\npackage com.client.ui;\r\n\r\nimport com.client.App;\r\nimport com.client.managers.RoomManager;\r\n\r\nimport javafx.geometry.Pos;\r\nimport javafx.scene.control.Button;\r\nimport javafx.scene.control.Label;\r\nimport javafx.scene.layout.HBox;\r\nimport javafx.scene.layout.VBox;\r\nimport javafx.scene.paint.Color;\r\nimport javafx.scene.text.Font;\r\nimport javafx.scene.text.FontWeight;\r\n\r\npublic class GameOverPopup extends VBox {\r\n\r\n    private int voteCount = 0;\r\n    private final int MIN_VOTES = 3;\r\n    private Label lblVotes;\r\n    private Button btnRematch;\r\n\r\n    public GameOverPopup(boolean isWin) {\r\n        this.setAlignment(Pos.CENTER);\r\n        this.setSpacing(20);\r\n        this.setStyle(\"-fx-background-color: rgba(0, 0, 0, 0.9); -fx-padding: 40; -fx-background-radius: 20;\");\r\n        this.setMaxSize(500, 400);\r\n\r\n        Label title = new Label(isWin ? \"VICTORY!\" : \"YOU DIED\");\r\n        title.setFont(Font.font(\"Segoe UI\", FontWeight.BOLD, 48));\r\n        title.setTextFill(isWin ? Color.GOLD : Color.RED);\r\n\r\n        // --- REMATCH SECTION ---\r\n        lblVotes = new Label(\"Rematch Votes: 0/\" + MIN_VOTES);\r\n        lblVotes.setTextFill(Color.WHITE);\r\n        lblVotes.setFont(Font.font(18));\r\n\r\n        btnRematch = new Button(\"Vote Rematch\");\r\n        styleButton(btnRematch, \"#2980b9\"); // Biru\r\n\r\n        btnRematch.setOnAction(e -> handleVote());\r\n\r\n        // Tombol Host (Accept Rematch) - Awalnya hidden\r\n        Button btnHostAccept = new Button(\"START REMATCH\");\r\n        styleButton(btnHostAccept, \"#27ae60\"); // Hijau\r\n        btnHostAccept.setVisible(false); // Muncul jika vote cukup & user adalah host\r\n\r\n        // Logic Simulasi jika vote terpenuhi\r\n        btnHostAccept.setOnAction(e -> {\r\n            App.startGame(App.currentStage); // Restart Game\r\n        });\r\n\r\n        // --- LEAVE BUTTON ---\r\n        Button btnLeave = new Button(\"Leave Room\");\r\n        styleButton(btnLeave, \"#c0392b\"); // Merah\r\n        btnLeave.setOnAction(e -> {\r\n            RoomManager.playerLeft(\"Player 1 (You)\"); // Trigger logic keluar\r\n            SceneManager.toLobby();\r\n        });\r\n\r\n        HBox buttonBox = new HBox(20, btnLeave, btnRematch);\r\n        buttonBox.setAlignment(Pos.CENTER);\r\n\r\n        this.getChildren().addAll(title, lblVotes, buttonBox, btnHostAccept);\r\n\r\n        // Simpan referensi button host biar bisa diupdate\r\n        this.btnHostStart = btnHostAccept;\r\n    }\r\n    \r\n    private Button btnHostStart;\r\n\r\n    private void handleVote() {\r\n        btnRematch.setDisable(true); // Disable biar gak spam vote\r\n        btnRematch.setText(\"Voted!\");\r\n        \r\n        // SIMULASI: Anggap player lain langsung setuju\r\n        voteCount++; // Vote kita\r\n        updateVoteUI();\r\n\r\n        // Simulasi delay bot voting (pake thread sleep ala-ala atau langsung aja)\r\n        voteCount += 2; // Simulasi 2 player lain vote\r\n        updateVoteUI();\r\n    }\r\n\r\n    private void updateVoteUI() {\r\n        lblVotes.setText(\"Rematch Votes: \" + voteCount + \"/\" + MIN_VOTES);\r\n        \r\n        // Jika vote cukup DAN kita adalah HOST -> Tampilkan tombol Start\r\n        if (voteCount >= MIN_VOTES && RoomManager.isHost()) {\r\n            btnHostStart.setVisible(true);\r\n        }\r\n    }\r\n\r\n    private void styleButton(Button btn, String color) {\r\n        btn.setStyle(\"-fx-background-color: \" + color + \"; -fx-text-fill: white; -fx-font-size: 16px; -fx-font-weight: bold;\");\r\n        btn.setPrefSize(160, 40);\r\n    }\r\n}"
        }
    ]
}